Imagedetection/Base_detection.py
Imagedetection/Imagedetection.py
Imagedetection/__init__.py
robotframework_imagedetection-0.4.6.dist-info/LICENSE
robotframework_imagedetection-0.4.6.dist-info/METADATA
robotframework_imagedetection-0.4.6.dist-info/WHEEL
robotframework_imagedetection-0.4.6.dist-info/top_level.txt
robotframework_imagedetection-0.4.6.dist-info/RECORD
